pymarkdownroh/__init__.py
pymarkdownroh/__main__.py
pymarkdownroh/mdblockquote.py
pymarkdownroh/mdcode.py
pymarkdownroh/mdformat.py
pymarkdownroh/mdheadlines.py
pymarkdownroh/mdimages.py
pymarkdownroh/mdlinks.py
pymarkdownroh/mdlists.py
pymarkdownroh-0.0.1.dist-info/licenses/LICENSE
pymarkdownroh-0.0.1.dist-info/METADATA
pymarkdownroh-0.0.1.dist-info/WHEEL
pymarkdownroh-0.0.1.dist-info/top_level.txt
pymarkdownroh-0.0.1.dist-info/RECORD
