Metadata-Version: 2.4
Name: pymarkdownroh
Version: 0.0.1
Summary: A python package to create markdown text.
Author: IT-Administrators
Maintainer: IT-Administrators
License: MIT License
Project-URL: Homepage, https://github.com/IT-Administrators/pymarkdownroh
Keywords: markdown,md,text,template
Classifier: Programming Language :: Python :: 3
Classifier: License :: OSI Approved :: MIT License
Classifier: Operating System :: OS Independent
Requires-Python: >=3.7
License-File: LICENSE
Dynamic: license-file
